langchain_camino/__init__.py
langchain_camino/_sdk_wrapper.py
langchain_camino/_utilities.py
langchain_camino/camino_journey.py
langchain_camino/camino_query.py
langchain_camino/camino_search.py
langchain_camino/main.py
langchain_camino/py.typed
langchain_camino-0.1.0.dist-info/METADATA
langchain_camino-0.1.0.dist-info/WHEEL
langchain_camino-0.1.0.dist-info/licenses/LICENSE
langchain_camino-0.1.0.dist-info/RECORD
