Metadata-Version: 2.4
Name: langchain-camino
Version: 0.1.0
Summary: An integration package connecting Camino AI Reality Grounding API and LangChain
License-File: LICENSE
Requires-Python: >=3.9
Requires-Dist: camino-ai-sdk>=0.1.0
Requires-Dist: langchain-core>=0.3.15
Requires-Dist: langchain>=0.3.20
Requires-Dist: pydantic>=2.0.0
Provides-Extra: lint
Requires-Dist: mypy>=1.15.0; extra == 'lint'
Requires-Dist: ruff>=0.5; extra == 'lint'
Requires-Dist: types-requests>=2.32.0.20250328; extra == 'lint'
Provides-Extra: test
Requires-Dist: langchain-tests>=0.3.5; extra == 'test'
Requires-Dist: pytest-asyncio>=0.23.2; extra == 'test'
Requires-Dist: pytest-socket>=0.7.0; extra == 'test'
Requires-Dist: pytest>=7.4.3; extra == 'test'
